python_bean/__init__.py
python_bean/database.py
python_bean/document_similar.py
python_bean/fake_requests.py
python_bean/send_email.py
python_bean/ssh_client.py
python_bean-0.0.4.dist-info/DESCRIPTION.rst
python_bean-0.0.4.dist-info/METADATA
python_bean-0.0.4.dist-info/RECORD
python_bean-0.0.4.dist-info/WHEEL
python_bean-0.0.4.dist-info/metadata.json
python_bean-0.0.4.dist-info/top_level.txt
