Metadata-Version: 2.0
Name: python-bean
Version: 0.0.4
Summary: some util collection for python
Home-page: https://github.com/mouday/PythonBean
Author: Peng Shiyu
Author-email: pengshiyuyx@gmail.com
License: UNKNOWN
Platform: UNKNOWN
Classifier: Programming Language :: Python :: 2.7
Classifier: Programming Language :: Python :: 3.6
Classifier: License :: OSI Approved :: MIT License
Classifier: Operating System :: OS Independent
Requires-Dist: gensim (>=3.7.1)
Requires-Dist: jieba (>=0.39)
Requires-Dist: requests (>=2.20.1)
